setup.cfg
setup.py
trac2google/__init__.py
trac2google/cal.py
trac2google/config.py
trac2google/fise_pontaj.py
trac2google/redmine.py
trac2google/trac.py
trac2google/urlshortener.py
trac2google/utils.py
trac2google.egg-info/PKG-INFO
trac2google.egg-info/SOURCES.txt
trac2google.egg-info/dependency_links.txt
trac2google.egg-info/entry_points.txt
trac2google.egg-info/not-zip-safe
trac2google.egg-info/requires.txt
trac2google.egg-info/top_level.txt