Metadata-Version: 1.0
Name: trac2google
Version: 0.5
Summary: A simple script that will read a Trac timeline RSS feed, look for tickets and put them on a timesheet calendar in Google
Home-page: http://bitbucket.org/tiberiuichim/trac2google
Author: Tiberiu Ichim
Author-email: tibi@pixelblaster.ro
License: GPL
Platform: UNKNOWN
